[
  {
    "Municipio": "Publicado Prefeitura sem Nome",
    "Mes": "01",
    "TotalLicitacoes": 23
  },
  {
    "Municipio": "Publicado Prefeitura sem Nome",
    "Mes": "02",
    "TotalLicitacoes": 23
  },
  {
    "Municipio": "Publicado Prefeitura sem Nome",
    "Mes": "03",
    "TotalLicitacoes": 46
  },
  {
    "Municipio": "Publicado Prefeitura sem Nome",
    "Mes": "04",
    "TotalLicitacoes": 39
  },
  {
    "Municipio": "Publicado Prefeitura sem Nome",
    "Mes": "05",
    "TotalLicitacoes": 36
  },
  {
    "Municipio": "Publicado Prefeitura sem Nome",
    "Mes": "06",
    "TotalLicitacoes": 36
  },
  {
    "Municipio": "Publicado Prefeitura sem Nome",
    "Mes": "07",
    "TotalLicitacoes": 42
  },
  {
    "Municipio": "Publicado Prefeitura sem Nome",
    "Mes": "08",
    "TotalLicitacoes": 61
  },
  {
    "Municipio": "Publicado Prefeitura sem Nome",
    "Mes": "09",
    "TotalLicitacoes": 35
  },
  {
    "Municipio": "Publicado Prefeitura sem Nome",
    "Mes": "10",
    "TotalLicitacoes": 32
  },
  {
    "Municipio": "Publicado Prefeitura sem Nome",
    "Mes": "11",
    "TotalLicitacoes": 34
  },
  {
    "Municipio": "Publicado Prefeitura sem Nome",
    "Mes": "12",
    "TotalLicitacoes": 36
  }
]